mongodb_connect/__init__.py
mongodb_connect/mongo_crud.py
databaseautomation_ajit-0.0.2.dist-info/METADATA
databaseautomation_ajit-0.0.2.dist-info/WHEEL
databaseautomation_ajit-0.0.2.dist-info/top_level.txt
databaseautomation_ajit-0.0.2.dist-info/RECORD
